{"nodes": [{"id": "calbindin\u2010positive pyramidal"}, {"id": "sequential activity"}, {"id": "outer border"}, {"id": "dendritic spikes"}, {"id": "polar cells"}, {"id": "goal locations"}, {"id": "cell migration"}, {"id": "place cells"}, {"id": "path integration"}, {"id": "oscillatory interference"}, {"id": "hippocampal formation"}, {"id": "grid cells"}, {"id": "border cell"}, {"id": "entorhinal cortex"}, {"id": "place field"}, {"id": "spatial periodicity"}, {"id": "place cell"}, {"id": "place fields"}, {"id": "border cells"}, {"id": "cell polarity"}, {"id": "etruscan shrews"}, {"id": "dimensional space"}, {"id": "calbindin patches"}, {"id": "spatial information"}, {"id": "grid-cell-like representations"}, {"id": "grid cell"}], "links": [{"source": "border cells", "target": "outer border", "value": 10}, {"source": "place cell", "target": "sequential activity", "value": 10}, {"source": "grid cells", "target": "place cells", "value": 10}, {"source": "entorhinal cortex", "target": "hippocampal formation", "value": 10}, {"source": "place cell", "target": "dendritic spikes", "value": 10}, {"source": "grid cell", "target": "path integration", "value": 10}, {"source": "entorhinal cortex", "target": "calbindin\u2010positive pyramidal", "value": 10}, {"source": "place cell", "target": "place cells", "value": 10}, {"source": "grid cells", "target": "border cells", "value": 10}, {"source": "grid cells", "target": "grid cell", "value": 10}, {"source": "place cell", "target": "dimensional space", "value": 10}, {"source": "place cells", "target": "place fields", "value": 10}, {"source": "grid cell", "target": "grid cells", "value": 10}, {"source": "place cells", "target": "spatial information", "value": 10}, {"source": "place cells", "target": "place cell", "value": 10}, {"source": "place cell", "target": "place field", "value": 10}, {"source": "border cells", "target": "cell polarity", "value": 10}, {"source": "grid cell", "target": "oscillatory interference", "value": 10}, {"source": "place cells", "target": "grid cells", "value": 10}, {"source": "entorhinal cortex", "target": "spatial periodicity", "value": 10}, {"source": "grid cells", "target": "place cell", "value": 10}, {"source": "grid cell", "target": "entorhinal cortex", "value": 10}, {"source": "border cells", "target": "border cell", "value": 10}, {"source": "border cells", "target": "polar cells", "value": 10}, {"source": "entorhinal cortex", "target": "etruscan shrews", "value": 10}, {"source": "grid cell", "target": "grid-cell-like representations", "value": 10}, {"source": "grid cells", "target": "entorhinal cortex", "value": 10}, {"source": "border cells", "target": "cell migration", "value": 10}, {"source": "place cells", "target": "goal locations", "value": 10}, {"source": "entorhinal cortex", "target": "calbindin patches", "value": 10}]}